CustomGPT/__init__.py
CustomGPT/custom_gpt.py
src/__init__.py
src/custom_gpt.py
CustomGPT-1.0.0.dist-info/LICENSE
CustomGPT-1.0.0.dist-info/METADATA
CustomGPT-1.0.0.dist-info/WHEEL
CustomGPT-1.0.0.dist-info/top_level.txt
CustomGPT-1.0.0.dist-info/RECORD
