Metadata-Version: 2.1
Name: CustomGPT
Version: 1.0.0
Summary: A package for interacting with GPT-4 models (and older) without using the OpenAI API.
Home-page: https://github.com/NLmeng/CustomGPT
Author: Lymeng Naret
Author-email: lymengnaret@yahoo.com
Classifier: Development Status :: 3 - Alpha
Classifier: Intended Audience :: Developers
Classifier: License :: OSI Approved :: MIT License
Classifier: Programming Language :: Python :: 3
Classifier: Programming Language :: Python :: 3.6
Classifier: Programming Language :: Python :: 3.7
Classifier: Programming Language :: Python :: 3.8
Classifier: Programming Language :: Python :: 3.9
Classifier: Programming Language :: Python :: 3.10
Classifier: Programming Language :: Python :: 3.11
License-File: LICENSE
Requires-Dist: requests (==2.28.2)
Requires-Dist: python-dotenv (==1.0.0)
